cashd_core/__init__.py
cashd_core/backup.py
cashd_core/const.py
cashd_core/data.py
cashd_core/fmt.py
cashd_core/prefs.py
cashd_core-0.3.4.dist-info/METADATA
cashd_core-0.3.4.dist-info/WHEEL
cashd_core-0.3.4.dist-info/entry_points.txt
cashd_core-0.3.4.dist-info/top_level.txt
cashd_core-0.3.4.dist-info/RECORD
